seance4d/Hmm1.mp3
seance4d/Hmm2.mp3
seance4d/Hmm3.mp3
seance4d/__init__.py
seance4d/cached.json
seance4d/cached_1.mp3
seance4d/cached_10.mp3
seance4d/cached_11.mp3
seance4d/cached_12.mp3
seance4d/cached_13.mp3
seance4d/cached_14.mp3
seance4d/cached_15.mp3
seance4d/cached_16.mp3
seance4d/cached_17.mp3
seance4d/cached_18.mp3
seance4d/cached_19.mp3
seance4d/cached_2.mp3
seance4d/cached_20.mp3
seance4d/cached_21.mp3
seance4d/cached_22.mp3
seance4d/cached_23.mp3
seance4d/cached_24.mp3
seance4d/cached_25.mp3
seance4d/cached_26.mp3
seance4d/cached_27.mp3
seance4d/cached_28.mp3
seance4d/cached_29.mp3
seance4d/cached_3.mp3
seance4d/cached_30.mp3
seance4d/cached_4.mp3
seance4d/cached_5.mp3
seance4d/cached_6.mp3
seance4d/cached_7.mp3
seance4d/cached_8.mp3
seance4d/cached_9.mp3
seance4d/config.py
seance4d/error.mp3
seance4d/holding.mp3
seance4d/main.py
seance4d/open_ai.py
seance4d/text_parser.py
seance4d/text_to_speech.py
seance4d/welcome.mp3
seance4d-0.0.60.dist-info/METADATA
seance4d-0.0.60.dist-info/WHEEL
seance4d-0.0.60.dist-info/top_level.txt
seance4d-0.0.60.dist-info/RECORD
